{
  "stats": {
    "num_docs": 20
  },
  "keywords": [
    {
      "keyword": "교육",
      "score": 3.8401709667171264
    },
    {
      "keyword": "디지털",
      "score": 3.3804826769181013
    },
    {
      "keyword": "보안",
      "score": 2.7563380607487615
    },
    {
      "keyword": "밝혔다",
      "score": 2.7037354723221547
    },
    {
      "keyword": "대상으로",
      "score": 2.49946841112578
    },
    {
      "keyword": "경북",
      "score": 2.463873055592236
    },
    {
      "keyword": "프로",
      "score": 2.2108350698813473
    },
    {
      "keyword": "서비스",
      "score": 2.1971102701313474
    },
    {
      "keyword": "미래",
      "score": 2.180504848112693
    },
    {
      "keyword": "글로벌",
      "score": 2.163752971720151
    },
    {
      "keyword": "인공지능",
      "score": 2.1373808865118784
    },
    {
      "keyword": "연수",
      "score": 1.9477537699509568
    },
    {
      "keyword": "특징주",
      "score": 1.9204607550620185
    },
    {
      "keyword": "있는",
      "score": 1.9137180439639998
    },
    {
      "keyword": "의료제품",
      "score": 1.8865896639626971
    },
    {
      "keyword": "수업",
      "score": 1.8523421633926813
    },
    {
      "keyword": "기술",
      "score": 1.8222198235836955
    },
    {
      "keyword": "전문",
      "score": 1.8099549620588116
    },
    {
      "keyword": "진행",
      "score": 1.806816511114639
    },
    {
      "keyword": "따르면",
      "score": 1.7854923507108715
    },
    {
      "keyword": "쿠페",
      "score": 1.776571156453921
    },
    {
      "keyword": "일까지",
      "score": 1.6424761004575537
    },
    {
      "keyword": "맞춤형",
      "score": 1.6415151040140241
    },
    {
      "keyword": "시간",
      "score": 1.6287620918606502
    },
    {
      "keyword": "학습",
      "score": 1.5543821971678735
    }
  ]
}