{
  "topics": [
    {
      "topic_id": 0,
      "top_words": [
        {
          "word": "반도체",
          "prob": 1.0
        },
        {
          "word": "성장",
          "prob": 0.6814988509098754
        },
        {
          "word": "이는",
          "prob": 0.6099514163173899
        },
        {
          "word": "이상",
          "prob": 0.4503005776704113
        },
        {
          "word": "기술",
          "prob": 0.3614612995863044
        },
        {
          "word": "영향을",
          "prob": 0.2940049734243931
        },
        {
          "word": "핵심",
          "prob": 0.2484623117638021
        },
        {
          "word": "대비",
          "prob": 0.23775752937541889
        },
        {
          "word": "대해",
          "prob": 0.19279780677268493
        },
        {
          "word": "같은",
          "prob": 0.15609983664461113
        }
      ]
    },
    {
      "topic_id": 1,
      "top_words": [
        {
          "word": "oled",
          "prob": 1.0
        },
        {
          "word": "대비",
          "prob": 0.19006976202216747
        },
        {
          "word": "개발",
          "prob": 0.14066594221950074
        },
        {
          "word": "이를",
          "prob": 0.13814145549276566
        },
        {
          "word": "한국",
          "prob": 0.13563663134102094
        },
        {
          "word": "ai",
          "prob": 0.11476691134460434
        },
        {
          "word": "미래",
          "prob": 0.10060171088697245
        },
        {
          "word": "가장",
          "prob": 0.08837910935780088
        },
        {
          "word": "이상",
          "prob": 0.08267127306442307
        },
        {
          "word": "아니라",
          "prob": 0.07550423473886514
        }
      ]
    },
    {
      "topic_id": 2,
      "top_words": [
        {
          "word": "주제로",
          "prob": 1.0
        },
        {
          "word": "ai",
          "prob": 0.5089102591300904
        },
        {
          "word": "넘어",
          "prob": 0.4763654798123656
        },
        {
          "word": "미래",
          "prob": 0.42610752077271236
        },
        {
          "word": "개최했다",
          "prob": 0.3960673337029856
        },
        {
          "word": "산업",
          "prob": 0.2092437054100538
        },
        {
          "word": "아니라",
          "prob": 0.18514468234911627
        },
        {
          "word": "혁신을",
          "prob": 0.15690875611529817
        },
        {
          "word": "대해",
          "prob": 0.018105902412437966
        },
        {
          "word": "하는",
          "prob": 0.018034772121637867
        }
      ]
    },
    {
      "topic_id": 3,
      "top_words": [
        {
          "word": "특히",
          "prob": 1.0
        },
        {
          "word": "이를",
          "prob": 0.9997893730485395
        },
        {
          "word": "같은",
          "prob": 0.999747262061521
        },
        {
          "word": "결과",
          "prob": 0.9997005007710311
        },
        {
          "word": "한국",
          "prob": 0.9996379788178408
        },
        {
          "word": "산업",
          "prob": 0.9995469539918701
        },
        {
          "word": "디스플레이",
          "prob": 0.9993244058287675
        },
        {
          "word": "가장",
          "prob": 0.12493083366954215
        },
        {
          "word": "이상",
          "prob": 0.12493049798448852
        },
        {
          "word": "대해",
          "prob": 0.12493049724480261
        }
      ]
    },
    {
      "topic_id": 4,
      "top_words": [
        {
          "word": "디스플레이",
          "prob": 1.0
        },
        {
          "word": "결과",
          "prob": 0.27778800578067286
        },
        {
          "word": "한국",
          "prob": 0.2777717136054809
        },
        {
          "word": "가장",
          "prob": 0.034979483274694474
        },
        {
          "word": "이상",
          "prob": 0.034901152581605255
        },
        {
          "word": "이는",
          "prob": 0.034858453703445626
        },
        {
          "word": "oled",
          "prob": 0.034824335899994015
        },
        {
          "word": "대해",
          "prob": 0.03470937613521518
        },
        {
          "word": "넘어",
          "prob": 0.03470934759898566
        },
        {
          "word": "미래",
          "prob": 0.034709343990866025
        }
      ]
    },
    {
      "topic_id": 5,
      "top_words": [
        {
          "word": "ai",
          "prob": 1.0
        },
        {
          "word": "기술",
          "prob": 0.18474800584053494
        },
        {
          "word": "혁신을",
          "prob": 0.1811455339886606
        },
        {
          "word": "개발",
          "prob": 0.16433106442144482
        },
        {
          "word": "산업",
          "prob": 0.15748616973986806
        },
        {
          "word": "성장",
          "prob": 0.14764646701950826
        },
        {
          "word": "핵심",
          "prob": 0.1451736288523489
        },
        {
          "word": "미래",
          "prob": 0.10674308056707973
        },
        {
          "word": "됐다",
          "prob": 0.09009593040389136
        },
        {
          "word": "개최했다",
          "prob": 0.08139593146121515
        }
      ]
    },
    {
      "topic_id": 6,
      "top_words": [
        {
          "word": "지난",
          "prob": 1.0
        },
        {
          "word": "경우",
          "prob": 0.634099801370385
        },
        {
          "word": "등을",
          "prob": 0.5041660963049212
        },
        {
          "word": "특히",
          "prob": 0.4870011077093607
        },
        {
          "word": "한국",
          "prob": 0.4588524456098964
        },
        {
          "word": "가장",
          "prob": 0.44741553536130024
        },
        {
          "word": "한다",
          "prob": 0.3683936090348146
        },
        {
          "word": "하는",
          "prob": 0.36836396573407165
        },
        {
          "word": "이를",
          "prob": 0.32135851555405565
        },
        {
          "word": "같은",
          "prob": 0.3112120670543711
        }
      ]
    }
  ]
}