{
  "topics": [
    {
      "topic_id": 0,
      "top_words": [
        {
          "word": "oled",
          "prob": 1.0
        },
        {
          "word": "디스플레이",
          "prob": 0.9245268703736989
        },
        {
          "word": "ai",
          "prob": 0.7712399450840931
        },
        {
          "word": "중국",
          "prob": 0.5946733455030762
        },
        {
          "word": "산업",
          "prob": 0.5328891018144449
        },
        {
          "word": "기술",
          "prob": 0.5184343511331119
        },
        {
          "word": "tv",
          "prob": 0.5032108327913731
        },
        {
          "word": "아이폰",
          "prob": 0.4952233592550021
        },
        {
          "word": "기업",
          "prob": 0.42490282866399426
        },
        {
          "word": "새로운",
          "prob": 0.407892211119257
        }
      ]
    },
    {
      "topic_id": 1,
      "top_words": [
        {
          "word": "반도체",
          "prob": 1.0
        },
        {
          "word": "삼성전자",
          "prob": 0.6864744081348451
        },
        {
          "word": "메모리",
          "prob": 0.396443731965648
        },
        {
          "word": "뉴스1",
          "prob": 0.3678512801194913
        },
        {
          "word": "장비",
          "prob": 0.3575356062522348
        },
        {
          "word": "장중",
          "prob": 0.3141310624809487
        },
        {
          "word": "거래일",
          "prob": 0.2976588802771492
        },
        {
          "word": "마감했다",
          "prob": 0.2924093244981609
        },
        {
          "word": "주가",
          "prob": 0.2655697900623625
        },
        {
          "word": "코스피",
          "prob": 0.25525864939936127
        }
      ]
    }
  ]
}